flask_fontawesome/__init__.py
flask_fontawesome/static/css/all.css
flask_fontawesome/static/css/all.min.css
flask_fontawesome/static/css/brands.css
flask_fontawesome/static/css/brands.min.css
flask_fontawesome/static/css/fontawesome.css
flask_fontawesome/static/css/fontawesome.min.css
flask_fontawesome/static/css/solid.css
flask_fontawesome/static/css/solid.min.css
flask_fontawesome/static/css/svg-with-js.css
flask_fontawesome/static/css/svg-with-js.min.css
flask_fontawesome/static/css/v4-shims.css
flask_fontawesome/static/css/v4-shims.min.css
flask_fontawesome/static/js/all.js
flask_fontawesome/static/js/all.min.js
flask_fontawesome/static/js/brands.js
flask_fontawesome/static/js/brands.min.js
flask_fontawesome/static/js/fontawesome.js
flask_fontawesome/static/js/fontawesome.min.js
flask_fontawesome/static/js/solid.js
flask_fontawesome/static/js/solid.min.js
flask_fontawesome/static/js/v4-shims.js
flask_fontawesome/static/js/v4-shims.min.js
flask_fontawesome/static/metadata/categories.yml
flask_fontawesome/static/metadata/icons.json
flask_fontawesome/static/metadata/icons.yml
flask_fontawesome/static/metadata/shims.json
flask_fontawesome/static/metadata/shims.yml
flask_fontawesome/static/metadata/sponsors.yml
flask_fontawesome/static/sprites/brands.svg
flask_fontawesome/static/sprites/solid.svg
flask_fontawesome/static/svgs/brands/500px.svg
flask_fontawesome/static/svgs/brands/accessible-icon.svg
flask_fontawesome/static/svgs/brands/accusoft.svg
flask_fontawesome/static/svgs/brands/adn.svg
flask_fontawesome/static/svgs/brands/adversal.svg
flask_fontawesome/static/svgs/brands/affiliatetheme.svg
flask_fontawesome/static/svgs/brands/algolia.svg
flask_fontawesome/static/svgs/brands/alipay.svg
flask_fontawesome/static/svgs/brands/amazon-pay.svg
flask_fontawesome/static/svgs/brands/amazon.svg
flask_fontawesome/static/svgs/brands/amilia.svg
flask_fontawesome/static/svgs/brands/android.svg
flask_fontawesome/static/svgs/brands/angellist.svg
Flask_FontAwesome-0.1.5.dist-info/LICENSE-APACHE
Flask_FontAwesome-0.1.5.dist-info/LICENSE-MIT
Flask_FontAwesome-0.1.5.dist-info/METADATA
Flask_FontAwesome-0.1.5.dist-info/WHEEL
Flask_FontAwesome-0.1.5.dist-info/top_level.txt
Flask_FontAwesome-0.1.5.dist-info/RECORD
